wllib2/__init__.py
wllib2/wlib2coretest.py
wllib2/az_lib/WL_az_http_func_handler_lib.py
wllib2/az_lib/WL_az_mock_lib.py
wllib2/az_lib/__init__.py
wllib2/db_lib/__init__.py
wllib2/db_lib/db_utils.py
wllib2/env_lib/WLAppEnv.py
wllib2/env_lib/WLAzAppEnv.py
wllib2/env_lib/__init__.py
wllib2/env_lib/env_utils.py
wllib2/img_lib/ImgAzHandlers.py
wllib2/img_lib/__init__.py
wllib2/img_lib/img_utils.py
wllib2/lib_tests/__init__.py
wllib2/lib_tests/pkg_test1.py
wllib2/pdf_lib/PDFAzHandlers.py
wllib2/pdf_lib/__init__.py
wllib2/pdf_lib/pdf_utils.py
wllib2/test_lib/AzTestHandlers.py
wllib2/test_lib/__init__.py
wavelengthlib2-0.1.29.dist-info/METADATA
wavelengthlib2-0.1.29.dist-info/WHEEL
wavelengthlib2-0.1.29.dist-info/top_level.txt
wavelengthlib2-0.1.29.dist-info/RECORD
