Metadata-Version: 2.1
Name: wavelengthlib2
Version: 0.1.29
Summary: Wavelength library 2
Home-page: UNKNOWN
Author: Simon
Author-email: simon.elliott@wavelength.law
License: UNKNOWN
Platform: UNKNOWN
Classifier: Intended Audience :: Developers
Classifier: Operating System :: OS Independent
Classifier: Programming Language :: Python :: 3.7
Requires-Python: >=3.7
Requires-Dist: pyodbc (==4.0.30)
Requires-Dist: python-dateutil
Requires-Dist: configparser
Requires-Dist: pandas
Requires-Dist: numpy
Requires-Dist: datetime
Requires-Dist: requests
Requires-Dist: Unidecode
Requires-Dist: openpyxl (==3.0.3)
Requires-Dist: python-docx (==0.8.10)
Requires-Dist: PyPDF2 (==1.26.0)
Requires-Dist: pdf2image (==1.6.0)
Requires-Dist: matplotlib
Requires-Dist: docx
Requires-Dist: PyMuPDF (==1.16.18)
Requires-Dist: Pillow
